MANIFEST.in
README.md
setup.py
QSystem.egg-info/PKG-INFO
QSystem.egg-info/SOURCES.txt
QSystem.egg-info/dependency_links.txt
QSystem.egg-info/top_level.txt
armadillo-code/include/armadillo
armadillo-code/include/armadillo_bits/BaseCube_bones.hpp
armadillo-code/include/armadillo_bits/BaseCube_meat.hpp
armadillo-code/include/armadillo_bits/Base_bones.hpp
armadillo-code/include/armadillo_bits/Base_meat.hpp
armadillo-code/include/armadillo_bits/Col_bones.hpp
armadillo-code/include/armadillo_bits/Col_meat.hpp
armadillo-code/include/armadillo_bits/Cube_bones.hpp
armadillo-code/include/armadillo_bits/Cube_meat.hpp
armadillo-code/include/armadillo_bits/GenCube_bones.hpp
armadillo-code/include/armadillo_bits/GenCube_meat.hpp
armadillo-code/include/armadillo_bits/GenSpecialiser.hpp
armadillo-code/include/armadillo_bits/Gen_bones.hpp
armadillo-code/include/armadillo_bits/Gen_meat.hpp
armadillo-code/include/armadillo_bits/GlueCube_bones.hpp
armadillo-code/include/armadillo_bits/GlueCube_meat.hpp
armadillo-code/include/armadillo_bits/Glue_bones.hpp
armadillo-code/include/armadillo_bits/Glue_meat.hpp
armadillo-code/include/armadillo_bits/MapMat_bones.hpp
armadillo-code/include/armadillo_bits/MapMat_meat.hpp
armadillo-code/include/armadillo_bits/Mat_bones.hpp
armadillo-code/include/armadillo_bits/Mat_meat.hpp
armadillo-code/include/armadillo_bits/OpCube_bones.hpp
armadillo-code/include/armadillo_bits/OpCube_meat.hpp
armadillo-code/include/armadillo_bits/Op_bones.hpp
armadillo-code/include/armadillo_bits/Op_meat.hpp
armadillo-code/include/armadillo_bits/Proxy.hpp
armadillo-code/include/armadillo_bits/ProxyCube.hpp
armadillo-code/include/armadillo_bits/Row_bones.hpp
armadillo-code/include/armadillo_bits/Row_meat.hpp
armadillo-code/include/armadillo_bits/SizeCube_bones.hpp
armadillo-code/include/armadillo_bits/SizeCube_meat.hpp
armadillo-code/include/armadillo_bits/SizeMat_bones.hpp
armadillo-code/include/armadillo_bits/SizeMat_meat.hpp
armadillo-code/include/armadillo_bits/SpBase_bones.hpp
armadillo-code/include/armadillo_bits/SpBase_meat.hpp
armadillo-code/include/armadillo_bits/SpCol_bones.hpp
