Metadata-Version: 2.1
Name: QSystem
Version: 1.1.0
Summary: A quantum computing simulator for Python
Home-page: https://gitlab.com/evandro-crr/qsystem
Author: Bruno Gouvêa Taketani, Evandro Chagas Ribeiro da Rosa
Author-email: ev.crr97@gmail.com
License: UNKNOWN
Platform: UNKNOWN
Classifier: Programming Language :: Python :: 3
Classifier: Intended Audience :: Science/Research
Classifier: License :: OSI Approved :: MIT License
